{
    "@class": "com.kony.gen.viz.model.component.KVizLabel",
    "DNDConfig": null,
    "_margin_": [
        1,
        1,
        1,
        1
    ],
    "_padding_": [
        2,
        0,
        0,
        0
    ],
    "_skin_": "sd5b2c1a25164811ac396bd44e1b75ee",
    "_text_": "You Accepted the above User Acknowledgement on 01/18/2017",
    "_wrapping_": 2,
    "android": {
        "textStyle": {
            "letterSpacing": 0,
            "strikeThrough": false
        }
    },
    "canUpdateUI": true,
    "containerweight": 100,
    "contentalignment": 4,
    "id": "lblAcceptAck",
    "info": null,
    "ipad": {
        "psp": {
            "wrapping": 2
        }
    },
    "iphone": {
        "psp": {
            "wrapping": 2
        }
    },
    "isvisible": true,
    "kuid": "2deaa9384e8542de90887801e1065156",
    "name": "kony.ui.Label",
    "paddInPixel": [
        0,
        0,
        0,
        0
    ],
    "paddinginpixel": false,
    "parent": "vboxAcceptAck",
    "pf": "popupUserAcknowledgement",
    "tooltip": "",
    "wType": "Label"
}