{
    "__parentReadjusting__": false,
    "_padding_": [
        0,
        0,
        0,
        0
    ],
    "_skin_": "sdeb87f91b9741d68039bd376dd0b328",
    "_srcKuid_": "dc26fe2c829d4ed5be4cab145702e5ae",
    "canUpdateUI": true,
    "context": {},
    "dataDiffs": {
        "centerY": {
            "type": "string",
            "value": "50%"
        },
        "height": {
            "type": "ref",
            "value": "preferred"
        },
        "id": "lblsignout",
        "left": {
            "type": "string",
            "value": "35dp"
        },
        "text": "Logout",
        "textStyle": {},
        "width": {
            "type": "ref",
            "value": "preferred"
        },
        "zIndex": 1
    },
    "id": "lblsignout",
    "instanceOf": "dc26fe2c829d4ed5be4cab145702e5ae",
    "isvisible": true,
    "kuid": "m26a908f6d544d8eadaf19238b3f38a8",
    "masterInstance": true,
    "name": "kony.ui.Label",
    "parent": "fcsignout",
    "pf": "frmPatientRecords",
    "topLevelInstanceKUID": "m2ec7220dd77410ea699c23400dde44c",
    "wType": "Label"
}