{
    "@class": "com.kony.gen.viz.model.component.KVizTextArea2",
    "DNDConfig": null,
    "__parentReadjusting__": false,
    "_height_": {
        "type": "string",
        "value": "120dp"
    },
    "_left_": {
        "type": "string",
        "value": "5dp"
    },
    "_margin_": [
        2,
        2,
        2,
        2
    ],
    "_padding_": [
        2,
        2,
        2,
        2
    ],
    "_placeholder_": "",
    "_skin_": "seb45cfa20c545d8bbd9d1c50cef6aa0",
    "_text_": "",
    "_top_": {
        "type": "string",
        "value": "2%"
    },
    "_width_": {
        "type": "string",
        "value": "90%"
    },
    "autocapitalize": "none",
    "autocomplete": false,
    "autocorrect": false,
    "autofilter": false,
    "canUpdateUI": true,
    "closebuttontext": "",
    "containerheight": "",
    "containerheightmode": 1,
    "containerweight": 100,
    "contentalignment": 1,
    "disabledSkins": {},
    "focusskin": "seb45cfa20c545d8bbd9d1c50cef6aa0",
    "id": "txtAreaDescription",
    "ide_onDone": "AS_TextArea_b288a996b1244f0d8786ce6fa43fa05e",
    "ide_onTextChange": "AS_TextArea_fbfdcd5bc0b94bfd9ad335d95d23fdb0",
    "info": null,
    "isvisible": true,
    "keyboardstyle": "A",
    "keyboardtype": "A",
    "kuid": "i8a7dcf41fb144298025aec6ec951ad5",
    "mode": "A",
    "name": "kony.ui.TextArea2",
    "numberofvisiblelines": 3,
    "parent": "FlexContainer0h98f0e1b741c4e",
    "pf": "frmNotificationDashboard",
    "securetextentry": false,
    "showoprogressindicator": false,
    "showprogressindicator": false,
    "textinputmode": "A",
    "viewtype": "default",
    "wType": "TextArea",
    "zindex": 1
}