{
    "DNDConfig": null,
    "_height_": {
        "type": "string",
        "value": "50dp"
    },
    "_margin_": [
        0,
        0,
        0,
        0
    ],
    "_orientation_": 6,
    "_padding_": [
        0,
        0,
        0,
        0
    ],
    "_percent_": true,
    "_skin_": "sa1111ea6188450386950c0abff2a271",
    "allboxes": [],
    "autogrowmode": 0,
    "canUpdateUI": true,
    "children": [
        "lblLine",
        "imgBackground",
        "lblTestType",
        "fcUpload"
    ],
    "clipbounds": true,
    "containerId": true,
    "containerweight": 100,
    "desktopweb": {
        "psp": {
            "hoverSkin": "sc7a69c7b2a5448c993ef880c865f670"
        }
    },
    "enablescrolling": true,
    "id": "fcTestResult",
    "info": null,
    "isTemplate": true,
    "isvisible": true,
    "kuid": "f3b45aae8ec6455f9c625483eb5c06df",
    "layouttype": 2,
    "name": "kony.ui.FlexContainer",
    "parent": "segTestResult",
    "pf": "segTestResult",
    "snapgridsize": 10,
    "snaptogrid": true,
    "wType": "FlexContainer",
    "widgetalignment": 1
}