{
    "DNDConfig": null,
    "__parentReadjusting__": false,
    "_height_": {
        "type": "ref",
        "value": "preferred"
    },
    "_left_": {
        "type": "string",
        "value": "0dp"
    },
    "_margin_": [
        0,
        0,
        0,
        0
    ],
    "_orientation_": 6,
    "_padding_": [
        0,
        0,
        0,
        0
    ],
    "_percent_": true,
    "_skin_": "sc056ab1d36f4ad6bd58cee1b8095a85",
    "_top_": {
        "type": "string",
        "value": "0dp"
    },
    "_width_": {
        "type": "string",
        "value": "100%"
    },
    "allboxes": [],
    "autogrowmode": 1,
    "canUpdateUI": true,
    "children": [
        "btnwoundsummary",
        "btnencounters",
        "btnpatientrecords",
        "Copybtnpatientrecords0g33b8a4e4bdf42",
        "btnpatienttask"
    ],
    "clipbounds": true,
    "containerweight": 100,
    "enablescrolling": true,
    "id": "fctreatmentbar",
    "info": null,
    "isvisible": true,
    "kuid": "4ebfc0d2938a4840973b36fa47790cc7",
    "layouttype": 3,
    "name": "kony.ui.FlexContainer",
    "parent": "fscbody",
    "pf": "frmPatientSummary",
    "snapgridsize": 10,
    "snaptogrid": true,
    "wType": "FlexContainer",
    "widgetalignment": 1,
    "zindex": 1
}