{
    "AS_Button_dee8a4a3508847a6bd51031172f68dfa": {
        "id": "AS_Button_dee8a4a3508847a6bd51031172f68dfa",
        "type": "ACTION_SEQUENCE",
        "params": [{
            "datatype": "collection",
            "name": "eventobject"
        }, {
            "datatype": "collection",
            "name": "context"
        }],
        "contextObj": {
            "name": "segsystemnotificationlist",
            "type": "templates",
            "platform": "",
            "KUID": "d464b9e354f6408ab3d88169f853e3bb"
        },
        "language": "js",
        "actions": [{
            "id": "INVOKE_FUNCTION___f859e41b6cef4e508cde3044f8e5d681",
            "type": "INVOKE_FUNCTION",
            "sequenceKUID": "frmNotificationDashboard_editNotification",
            "display": "frmNotificationDashboard_editNotification",
            "inputparams": [{
                "name": "selected",
                "value": "context"
            }],
            "parentId": null,
            "callbackType": null,
            "disabled": null,
            "source": "module"
        }]
    }
}