{
    "AS_FlexContainer_fc58312f75ce4dd6b6466ddd4598eb32": {
        "id": "AS_FlexContainer_fc58312f75ce4dd6b6466ddd4598eb32",
        "type": "ACTION_SEQUENCE",
        "params": [{
            "datatype": "collection",
            "name": "eventobject"
        }],
        "contextObj": {
            "type": "forms",
            "platform": null,
            "KUID": "fc1b57512dfa44149ee26abddb494696"
        },
        "sourceObj": {
            "itemKUID": "aea4d3ca881f4b469750e57bfaaaf48b",
            "widgetKUID": "511d130ddaf54948b93320874c983eb7",
            "evt": "onClick",
            "platform": null
        },
        "language": "js",
        "actions": [{
            "id": "NAMED_ACTION____a62f7748139e4930bbc41fd1754c3be5",
            "type": "NAMED_ACTION",
            "sequenceKUID": "AS_FlexContainer_68f9ff553459408a9d48b64cf63df781",
            "display": "AS_FlexContainer_68f9ff553459408a9d48b64cf63df781",
            "inputparams": [{
                "datatype": "collection",
                "name": "eventobject",
                "value": "eventobject"
            }],
            "parentId": null,
            "callbackType": null,
            "disabled": false,
            "isMasterInstanceAction": true
        }]
    }
}