{
    "AS_FlexContainer_8d9b0dad6e33464a880db783d0b3f43d": {
        "id": "AS_FlexContainer_8d9b0dad6e33464a880db783d0b3f43d",
        "type": "ACTION_SEQUENCE",
        "name": "frmPAtientRecords_fcPrint_onClick",
        "params": [{
            "datatype": "collection",
            "name": "eventobject"
        }],
        "contextObj": {
            "name": "frmPatientRecords",
            "type": "forms",
            "platform": "",
            "KUID": "2dadc999bf6b45babe7b7fd8757e2f92"
        },
        "sourceObj": {
            "itemKUID": "aea4d3ca881f4b469750e57bfaaaf48b",
            "widgetKUID": "04b61b0bb86343a1a9a4563167f680b0",
            "evt": "onClick",
            "platform": null
        },
        "language": "js",
        "actions": [{
            "id": "NAMED_ACTION____c9b69f3207c8468b97b25bab7773c3c5",
            "type": "NAMED_ACTION",
            "sequenceKUID": "AS_FlexContainer_365e100466c34004b7d22542afc4bcdb",
            "display": "AS_FlexContainer_365e100466c34004b7d22542afc4bcdb",
            "inputparams": [{
                "datatype": "collection",
                "name": "eventobject",
                "value": "eventobject"
            }],
            "parentId": null,
            "callbackType": null,
            "disabled": false,
            "isMasterInstanceAction": true
        }]
    }
}