{
    "DNDConfig": null,
    "__parentReadjusting__": false,
    "_height_": {
        "type": "string",
        "value": "50dp"
    },
    "_margin_": [
        0,
        0,
        0,
        0
    ],
    "_orientation_": 6,
    "_padding_": [
        0,
        0,
        0,
        0
    ],
    "_percent_": true,
    "_right_": {
        "type": "string",
        "value": "27%"
    },
    "_skin_": "sa1111ea6188450386950c0abff2a271",
    "_top_": {
        "type": "string",
        "value": "12dp"
    },
    "_width_": {
        "type": "string",
        "value": "380dp"
    },
    "allboxes": [],
    "autogrowmode": 0,
    "canUpdateUI": true,
    "children": [
        "lblSearch",
        "tbpatientsearch",
        "fcsearchicon"
    ],
    "clipbounds": true,
    "containerweight": 100,
    "enablescrolling": true,
    "id": "fcSearchPatient",
    "info": null,
    "isvisible": true,
    "kuid": "83f10ca975b647e9877cd2df009def7a",
    "layouttype": 2,
    "name": "kony.ui.FlexContainer",
    "parent": "fcdashboardsubheader",
    "pf": "frmWCCDashboard",
    "snapgridsize": 10,
    "snaptogrid": true,
    "wType": "FlexContainer",
    "widgetalignment": 1,
    "zindex": 2
}