{
    "@class": "com.kony.gen.viz.model.component.KVizImage2",
    "DNDConfig": null,
    "__parentReadjusting__": false,
    "_base64_": null,
    "_height_": {
        "type": "string",
        "value": "100%"
    },
    "_left_": {
        "type": "string",
        "value": "0dp"
    },
    "_margin_": [
        0,
        0,
        0,
        0
    ],
    "_padding_": [
        0,
        0,
        0,
        0
    ],
    "_skin_": "scbda1b6e03f4b429e87cb85b8d1f892",
    "_src_": "info.png",
    "_top_": {
        "type": "string",
        "value": "0dp"
    },
    "_width_": {
        "type": "string",
        "value": "100%"
    },
    "canUpdateUI": true,
    "containerweight": 100,
    "context": {
        "channel": "desktop",
        "formID": "frmWCCDashboard",
        "platform": "desktopweb",
        "templateType": "forms",
        "topLevelBox": null
    },
    "id": "imgInfo90",
    "imagescalemode": 1,
    "info": null,
    "invokedProperty": "src",
    "isvisible": true,
    "kuid": "3c724162c7d14dc295700a9fdd3ef8ce",
    "name": "kony.ui.Image2",
    "parent": "fcInfo90",
    "pf": "frmWCCDashboard",
    "srcType": 1,
    "wType": "Image",
    "widgetalignment": 5,
    "zindex": 1
}