{
    "AS_FlexContainer_9e309b407803490084599414c1253bc5": {
        "id": "AS_FlexContainer_9e309b407803490084599414c1253bc5",
        "type": "ACTION_SEQUENCE",
        "params": [{
            "datatype": "collection",
            "name": "eventobject"
        }],
        "language": "js",
        "actions": [{
            "id": "INVOKE_FUNCTION__ide_onClick_db504a4c590a409cbc823142b3723f37",
            "type": "INVOKE_FUNCTION",
            "sequenceKUID": "frmPatientList_onClickPatientList",
            "display": "frmPatientList_onClickPatientList",
            "inputparams": [{
                "name": "weeks",
                "value": "\"1\""
            }],
            "callbackType": null,
            "disabled": null,
            "source": "module"
        }]
    }
}