{
    "AS_FlexContainer_8d80ce901dc64a4196aa74d4b908d92d": {
        "id": "AS_FlexContainer_8d80ce901dc64a4196aa74d4b908d92d",
        "type": "ACTION_SEQUENCE",
        "params": [{
            "datatype": "collection",
            "name": "eventobject"
        }],
        "contextObj": {
            "type": "forms",
            "platform": null,
            "KUID": "d48a1f879b954935bd3773b07fc61725"
        },
        "sourceObj": {
            "itemKUID": "85f7d9af654845e7a601e5b444d74516",
            "widgetKUID": "b0f4a6e002474b14a900be83b8fb4e44",
            "evt": "onClick",
            "platform": null
        },
        "language": "js",
        "actions": [{
            "id": "NAMED_ACTION____33f24cbd5e614b93ac84ec2143a0ece5",
            "type": "NAMED_ACTION",
            "sequenceKUID": "AS_FlexContainer_779f0b711ddb4f4fb61a8078ce6c3bd6",
            "display": "AS_FlexContainer_779f0b711ddb4f4fb61a8078ce6c3bd6",
            "inputparams": [{
                "datatype": "collection",
                "name": "eventobject",
                "value": "eventobject"
            }],
            "parentId": null,
            "callbackType": null,
            "disabled": false,
            "isMasterInstanceAction": true
        }]
    }
}