{
    "AS_FlexContainer_57bd4f05c64e496c9c65d0c67ecfcad0": {
        "id": "AS_FlexContainer_57bd4f05c64e496c9c65d0c67ecfcad0",
        "type": "ACTION_SEQUENCE",
        "params": [{
            "datatype": "collection",
            "name": "eventobject"
        }],
        "contextObj": {
            "type": "forms",
            "platform": null,
            "KUID": "e270191b8c514a01bd805196f34fb273"
        },
        "sourceObj": {
            "itemKUID": "85f7d9af654845e7a601e5b444d74516",
            "widgetKUID": "673467e88add4c27b9d7afe71eb09835",
            "evt": "onClick",
            "platform": null
        },
        "language": "js",
        "actions": [{
            "id": "NAMED_ACTION____309d3587ece84d8e9f9f987867a8164d",
            "type": "NAMED_ACTION",
            "sequenceKUID": "AS_FlexContainer_92d17d32b57d407d9eca64b02ccde833",
            "display": "AS_FlexContainer_92d17d32b57d407d9eca64b02ccde833",
            "inputparams": [{
                "datatype": "collection",
                "name": "eventobject",
                "value": "eventobject"
            }],
            "parentId": null,
            "callbackType": null,
            "disabled": false,
            "isMasterInstanceAction": true
        }]
    }
}