{
    "AS_Image_ce906f31f1784d388b91b74275db9306": {
        "id": "AS_Image_ce906f31f1784d388b91b74275db9306",
        "type": "ACTION_SEQUENCE",
        "params": [{
            "datatype": "collection",
            "name": "eventobject"
        }, {
            "datatype": "string",
            "name": "x"
        }, {
            "datatype": "string",
            "name": "y"
        }],
        "contextObj": {
            "name": "frmPatientList",
            "type": "forms",
            "platform": "",
            "KUID": "6a5ac136946645f392c3702ef128575e"
        },
        "language": "js",
        "actions": [{
            "id": "INVOKE_FUNCTION___3252188bb07e414e9796898df059199d",
            "type": "INVOKE_FUNCTION",
            "sequenceKUID": "frmPatientList_show_sortpopup",
            "display": "frmPatientList_show_sortpopup",
            "inputparams": [{
                "name": "eventobject",
                "value": " eventobject"
            }],
            "parentId": null,
            "disabled": null,
            "source": "module"
        }]
    }
}