{
    "AS_Label_1552875b740b4bbe9b375389492e9ee7": {
        "id": "AS_Label_1552875b740b4bbe9b375389492e9ee7",
        "type": "ACTION_SEQUENCE",
        "params": [{
            "datatype": "collection",
            "name": "eventobject"
        }, {
            "datatype": "string",
            "name": "x"
        }, {
            "datatype": "string",
            "name": "y"
        }],
        "contextObj": {
            "name": "frmPatientList",
            "type": "forms",
            "platform": null,
            "KUID": "6a5ac136946645f392c3702ef128575e"
        },
        "language": "js",
        "actions": [{
            "id": "INVOKE_FUNCTION__ide_onTouchEnd_5512d7e85c0f4ebd87702baec73cc08f",
            "type": "INVOKE_FUNCTION",
            "sequenceKUID": "frmPatientList_onClickPatientList",
            "display": "frmPatientList_onClickPatientList",
            "inputparams": [{
                "name": "weeks",
                "value": "\"4\""
            }],
            "callbackType": null,
            "disabled": null,
            "source": "module"
        }]
    }
}