{
    "__parentReadjusting__": false,
    "_padding_": [
        0,
        0,
        0,
        0
    ],
    "_skin_": "s0486f18541d4eeca1dfa643713e14ed",
    "_srcKuid_": "668bcf621b7d40da9fee191b819161ee",
    "areflexpropsreferenced": false,
    "canUpdateUI": true,
    "children": [
        "imgreports",
        "lblreports"
    ],
    "context": {},
    "dataDiffs": {
        "clipBounds": true,
        "enableScrolling": true,
        "height": {
            "type": "string",
            "value": "45dp"
        },
        "id": "fcreports",
        "layoutType": 2,
        "left": "0dp",
        "snapGridSize": 10,
        "snapToGrid": true,
        "top": "0dp",
        "width": {
            "type": "string",
            "value": "100%"
        },
        "zIndex": 2
    },
    "id": "fcreports",
    "ide_onClick": "AS_FlexContainer_fe73deb613734328ba00650e6c12c7c2",
    "instanceOf": "668bcf621b7d40da9fee191b819161ee",
    "isdatareferenced": false,
    "isvisible": true,
    "kuid": "ma816001b0754591b09092ee5330c972",
    "masterInstance": true,
    "name": "kony.ui.FlexContainer",
    "parent": "fctopmenu",
    "pf": "frmNotificationDashboard",
    "topLevelInstanceKUID": "mba2251a7e2c4dbbb68a9280f10a4c22",
    "wType": "FlexContainer"
}